{
  "name": "text-animated-gradient",
  "type": "ui:components",
  "externalDependencies": [],
  "internalDependencies": [],
  "files": [
    {
      "name": "text-animated-gradient.tsx",
      "content": "export function TextAnimatedGradient() {\n  return (\n    <span className=\"inline-flex animate-text-gradient bg-gradient-to-r from-[#535353] via-[#c9c9c9] to-[#535353] bg-[200%_auto] bg-clip-text text-center text-base font-medium text-transparent dark:from-[#ACACAC] dark:via-[#363636] dark:to-[#ACACAC]\">\n      Text Animated Gradient\n    </span>\n  );\n}\n"
    }
  ]
}